stardrawer/__init__.py
stardrawer/drawer.py
stardrawer_led-1.0.4.dist-info/METADATA
stardrawer_led-1.0.4.dist-info/WHEEL
stardrawer_led-1.0.4.dist-info/top_level.txt
stardrawer_led-1.0.4.dist-info/RECORD
