Metadata-Version: 2.1
Name: stardrawer-led
Version: 1.0.4
Summary: 입력된 변 길이 만큼 정사각형 형태로 별을 찍습니다.
Home-page: https://github.com/eundonglee
Author: eundong
Author-email: cr3306@naver.com
License: MIT
Platform: UNKNOWN
Classifier: Programming Language :: Python :: 3
Classifier: License :: OSI Approved :: MIT License
Classifier: Operating System :: OS Independent
Requires-Dist: numpy
